django_private_chat2/__init__.py
django_private_chat2/admin.py
django_private_chat2/apps.py
django_private_chat2/models.py
django_private_chat2/serializers.py
django_private_chat2/urls.py
django_private_chat2/views.py
django_private_chat2/consumers/__init__.py
django_private_chat2/consumers/chat_consumer.py
django_private_chat2/consumers/db_operations.py
django_private_chat2/consumers/errors.py
django_private_chat2/consumers/message_types.py
django_private_chat2/migrations/0001_initial.py
django_private_chat2/migrations/0002_auto_20210329_2217.py
django_private_chat2/migrations/__init__.py
django_private_chat2/static/css/django_private_chat2.css
django_private_chat2/static/js/django_private_chat2.js
django_private_chat2/templates/django_private_chat2/base.html
django_private_chat2-1.0.2.dist-info/AUTHORS.rst
django_private_chat2-1.0.2.dist-info/LICENSE
django_private_chat2-1.0.2.dist-info/METADATA
django_private_chat2-1.0.2.dist-info/WHEEL
django_private_chat2-1.0.2.dist-info/top_level.txt
django_private_chat2-1.0.2.dist-info/RECORD
