Metadata-Version: 2.1
Name: django-private-chat2
Version: 1.0.2
Summary: Chat app for Django, powered by Django Channels, Websockets & Asyncio
Home-page: https://github.com/Bearle/django_private_chat2
Author: Bearle
Author-email: tech@bearle.ru
License: MIT
Keywords: django_private_chat2
Platform: UNKNOWN
Classifier: Development Status :: 4 - Beta
Classifier: Framework :: Django :: 3.0
Classifier: Framework :: Django :: 3.1
Classifier: Framework :: Django :: 3.2
Classifier: Framework :: Django :: 4.0
Classifier: Intended Audience :: Developers
Classifier: License :: OSI Approved :: MIT License
Classifier: Natural Language :: English
Classifier: Programming Language :: Python :: 3
Classifier: Programming Language :: Python :: 3.6
Classifier: Programming Language :: Python :: 3.7
Classifier: Programming Language :: Python :: 3.8
Classifier: Programming Language :: Python :: 3.9
Classifier: Programming Language :: Python :: 3.10
License-File: LICENSE
License-File: AUTHORS.rst
